gmice/ak07.py
gmice/fm11.py
gmice/gmice.py
gmice/wald99.py
gmice/wgrw12.py
esi_utils_gmice-1.0.1.dist-info/LICENSE.md
esi_utils_gmice-1.0.1.dist-info/METADATA
esi_utils_gmice-1.0.1.dist-info/WHEEL
esi_utils_gmice-1.0.1.dist-info/top_level.txt
esi_utils_gmice-1.0.1.dist-info/RECORD
