Metadata-Version: 2.1
Name: esi-utils-gmice
Version: 1.0.1
Summary: USGS Automated Ground Motion Processing Software
Author-email: Bruce Worden <cbworden@contractor.usgs.gov>, Eric Thompson <emthompsone@usgs.gov>, Mike Hearne <mhearne@usgs.gov>
License: License
Requires-Python: >=3.8
License-File: LICENSE.md
Requires-Dist: numpy<2.0.0
Requires-Dist: openquake.engine>=3.20
Requires-Dist: numba
Requires-Dist: fiona
Provides-Extra: build
Requires-Dist: build; extra == "build"
Requires-Dist: twine; extra == "build"
Requires-Dist: check-wheel-contents; extra == "build"
Provides-Extra: dev
Requires-Dist: build>=0.7.0; extra == "dev"
Requires-Dist: black>=21; extra == "dev"
Requires-Dist: flake8>=3.9; extra == "dev"
Requires-Dist: ipython>=7.26; extra == "dev"
Requires-Dist: pylint>=2.17; extra == "dev"
Provides-Extra: test
Requires-Dist: pytest>=6.2; extra == "test"
Requires-Dist: pytest-cov>=2.12; extra == "test"
Requires-Dist: pytest-console-scripts>=1.2; extra == "test"
Requires-Dist: vcrpy>=4.1; extra == "test"
